devtools_box_shadow/__init__.py
devtools_box_shadow-1.0.1.dist-info/METADATA
devtools_box_shadow-1.0.1.dist-info/WHEEL
devtools_box_shadow-1.0.1.dist-info/top_level.txt
devtools_box_shadow-1.0.1.dist-info/RECORD
