Metadata-Version: 2.1
Name: devtools-box-shadow
Version: 1.0.1
Summary: CSS box-shadow generator
Home-page: https://devtools.at/tools/box-shadow
Author: DevTools.at
Author-email: hello@devtools.at
Project-URL: Homepage, https://devtools.at/tools/box-shadow
Project-URL: Repository, https://github.com/devtools-at/box-shadow
Classifier: Development Status :: 4 - Beta
Classifier: Intended Audience :: Developers
Classifier: License :: OSI Approved :: MIT License
Classifier: Programming Language :: Python :: 3
Requires-Python: >=3.8
